forgeschema/__init__.py
forgeschema/asnschema.py
forgeschema/helpers.py
forgeschema/jsonschema.py
forgeschema/render.py
forgeschema/schema.py
forgeschema/types.py
forgeschema/xsdschema.py
forgeschema/console/console_scripts.py
forgeschema-0.1a10.dist-info/entry_points.txt
forgeschema-0.1a10.dist-info/LICENSE
forgeschema-0.1a10.dist-info/WHEEL
forgeschema-0.1a10.dist-info/METADATA
forgeschema-0.1a10.dist-info/RECORD
