Metadata-Version: 2.1
Name: forgeschema
Version: 0.1a10
Summary: forge-schema
Author-email: Mark Canterbury <markc@tencastle.com>
Requires-Python: >=3.12
Classifier: License :: OSI Approved :: MIT License
Requires-Dist: jsonschema >= 4.22
Requires-Dist: xmlschema >= 2.5.0
Requires-Dist: colorama >= 0.4.6
Requires-Dist: pytest ; extra == "test"
Requires-Dist: tests ; extra == "testpaths"
Provides-Extra: test
Provides-Extra: testpaths
